noop.cpython-311-x86_64-linux-gnu.so
sqlite_assert/__init__.py
sqlite_assert/assert0.so
sqlite_assert/version.py
sqlite_assert-0.1.0a50.dist-info/METADATA
sqlite_assert-0.1.0a50.dist-info/WHEEL
sqlite_assert-0.1.0a50.dist-info/top_level.txt
sqlite_assert-0.1.0a50.dist-info/RECORD
