Metadata-Version: 2.1
Name: sqlite-assert
Version: 0.1.0a50
Home-page: https://github.com/asg017/sqlite-assert
Author: Alex Garcia
License: MIT License, Apache License, Version 2.0
Project-URL: Issues, https://github.com/asg017/sqlite-assert/issues
Project-URL: CI, https://github.com/asg017/sqlite-assert/actions
Project-URL: Changelog, https://github.com/asg017/sqlite-assert/releases
Requires-Python: >=3.6
Provides-Extra: test
Requires-Dist: pytest ; extra == 'test'
